README.md
setup.py
cognito_code_grant/__init__.py
cognito_code_grant/authentication.py
cognito_code_grant/helpers.py
cognito_code_grant/signed_cookies.py
cognito_code_grant/views.py
cognito_code_grant.egg-info/PKG-INFO
cognito_code_grant.egg-info/SOURCES.txt
cognito_code_grant.egg-info/dependency_links.txt
cognito_code_grant.egg-info/requires.txt
cognito_code_grant.egg-info/top_level.txt