Metadata-Version: 2.1
Name: cognito-code-grant
Version: 1.0.30
Summary: A middleware and a set of handlers to handle Code Grant authentication with Cognito
Home-page: UNKNOWN
Author: STITCH (Aleksey Panov, Mario Brito, Gaston Lucero, Daniel Hengeveld)
Author-email: panovitch@gmail.com
License: MIT
Platform: UNKNOWN
Classifier: Development Status :: 5 - Production/Stable
Classifier: Environment :: Web Environment
Classifier: Framework :: Django
Classifier: Framework :: Django :: 2.2
Classifier: Intended Audience :: Developers
Classifier: Operating System :: OS Independent
Classifier: Programming Language :: Python
Classifier: Programming Language :: Python :: 3
Classifier: Programming Language :: Python :: 3 :: Only
Classifier: Programming Language :: Python :: 3.5
Classifier: Programming Language :: Python :: 3.6
Classifier: Programming Language :: Python :: 3.7
Classifier: Topic :: Software Development :: Libraries :: Python Modules
Classifier: License :: OSI Approved :: MIT License
Requires-Python: >=3.5
